netrun/__init__.py
netrun/validation/__init__.py
netrun/validation/custom_types.py
netrun/validation/datetime_utils.py
netrun/validation/decorators.py
netrun/validation/environment.py
netrun/validation/network.py
netrun/validation/security.py
netrun/validation/validators.py
netrun_validation-1.0.0.dist-info/METADATA
netrun_validation-1.0.0.dist-info/WHEEL
netrun_validation-1.0.0.dist-info/licenses/LICENSE
netrun_validation-1.0.0.dist-info/RECORD
