Metadata-Version: 2.4
Name: netrun-validation
Version: 1.0.0
Summary: Comprehensive Pydantic validators and custom types for Netrun Systems portfolio applications
Project-URL: Homepage, https://github.com/netrunsystems/netrun-validation
Project-URL: Documentation, https://docs.netrunsystems.com/validation
Project-URL: Repository, https://github.com/netrunsystems/netrun-validation
Project-URL: Issues, https://github.com/netrunsystems/netrun-validation/issues
Author-email: Daniel Garza <daniel@netrunsystems.com>
License: MIT
License-File: LICENSE
Keywords: custom-types,datetime,network,pydantic,security,validation,validators
Classifier: Development Status :: 5 - Production/Stable
Classifier: Framework :: Pydantic
Classifier: Framework :: Pydantic :: 2
Classifier: Intended Audience :: Developers
Classifier: License :: OSI Approved :: MIT License
Classifier: Programming Language :: Python :: 3
Classifier: Programming Language :: Python :: 3.10
Classifier: Programming Language :: Python :: 3.11
Classifier: Programming Language :: Python :: 3.12
Classifier: Topic :: Software Development :: Libraries :: Python Modules
Requires-Python: >=3.10
Requires-Dist: email-validator>=2.0.0
Requires-Dist: pydantic>=2.0.0
Provides-Extra: dev
Requires-Dist: black>=23.0.0; extra == 'dev'
Requires-Dist: mypy>=1.5.0; extra == 'dev'
Requires-Dist: pytest-asyncio>=0.21.0; extra == 'dev'
Requires-Dist: pytest-cov>=4.1.0; extra == 'dev'
Requires-Dist: pytest>=7.4.0; extra == 'dev'
Requires-Dist: ruff>=0.1.0; extra == 'dev'
